pyci/__init__.py
pyci/config.py
pyci/msg.py
pyci/server.py
pyci/utility.py
pyci/scripts/ci.py
pyci/templates/error.html
pyci/templates/error.txt
pyci/templates/failure.html
pyci/templates/failure.txt
pyci/templates/start.html
pyci/templates/start.txt
pyci/templates/success.html
pyci/templates/success.txt
pyci/templates/timeout.html
pyci/templates/timeout.txt
pyci-0.0.4.data/scripts/ci.py
pyci-0.0.4.dist-info/DESCRIPTION.rst
pyci-0.0.4.dist-info/METADATA
pyci-0.0.4.dist-info/metadata.json
pyci-0.0.4.dist-info/pbr.json
pyci-0.0.4.dist-info/RECORD
pyci-0.0.4.dist-info/top_level.txt
pyci-0.0.4.dist-info/WHEEL
