Metadata-Version: 2.0
Name: pyci
Version: 0.0.4
Summary: Continuous integration server for Github and MediaWiki.
Home-page: https://github.com/rosenbrockc/ci
Author: Conrad W Rosenbrock
Author-email: rosenbrockc@gmail.com
License: MIT
Platform: UNKNOWN
Classifier: Development Status :: 3 - Alpha
Classifier: Intended Audience :: Developers
Classifier: Natural Language :: English
Classifier: License :: OSI Approved :: MIT License
Classifier: Operating System :: MacOS
Classifier: Operating System :: Unix
Classifier: Programming Language :: Python
Classifier: Programming Language :: Python :: 2
Classifier: Programming Language :: Python :: 2.7
Classifier: Topic :: Software Development :: Libraries :: Python Modules
Requires-Dist: argparse
Requires-Dist: termcolor
Requires-Dist: dominate
Requires-Dist: mwclient
Requires-Dist: python-crontab
Requires-Dist: pygithub
